picoRV32_rom/uart.v
`ifndef UART_V
`define UART_V
 
 /*
  * This code was originally found at https://www.nandland.com/vhdl/modules/module-uart-serial-port-rs232.html
  * Slight modifications are done in order to improve readability and wrappers have been written in order to
  * facilitate integration with the PICORV32 
 */
 
module UART_TX 
   (
   input       i_Rst_L,
   input       i_Clock,
   input       i_TX_DV,		//control signal to start transmission
   input [7:0] i_TX_Byte,
   input [11:0] i_Clk_per_bit, // clk_frequency / bit_rate
   output reg  o_TX_Active_L, //output remains L during transmission
   output reg  o_TX_Serial,
   output reg  o_TX_Done
   );
 
  localparam IDLE         = 3'b000;
  localparam TX_START_BIT = 3'b001;
  localparam TX_DATA_BITS = 3'b010;
  localparam TX_STOP_BIT  = 3'b011;
  localparam CLEANUP      = 3'b100;
  
  reg [2:0] r_SM_Main;
  reg [11:0] r_Clock_Count;
  reg [2:0] r_Bit_Index;
  reg [7:0] r_TX_Data;


  // Purpose: Control TX state machine
  always @(posedge i_Clock) begin
    if (i_Rst_L == 0) begin
		r_SM_Main <= 3'b000;
		o_TX_Done <= 1'b0;
		o_TX_Active_L <= 1'b1;
    end else begin
		
		case (r_SM_Main)
			IDLE :
				begin
					o_TX_Serial   <= 1'b1;    // Drive Tx output line to High 
					o_TX_Done     <= 1'b0;	// Flag that Tx is ready to new transmission
					r_Clock_Count <= 0;
					r_Bit_Index   <= 0;
			  
					if (i_TX_DV == 1'b1) begin
						o_TX_Active_L <= 1'b0;
						r_TX_Data     <= i_TX_Byte;
						r_SM_Main     <= TX_START_BIT;
					end else
						r_SM_Main <= IDLE;
					end // case: IDLE
				
		  // Send out Start Bit. Start bit = 0
			TX_START_BIT :
				begin
					o_TX_Serial <= 1'b0;
				  
					// Wait i_Clk_per_bit-1 clock cycles for start bit to finish
					if (r_Clock_Count < i_Clk_per_bit-1) begin
						r_Clock_Count <= r_Clock_Count + 1;
						r_SM_Main     <= TX_START_BIT;
					end else begin
						r_Clock_Count <= 0;
						r_SM_Main     <= TX_DATA_BITS;
					end
				end // case: TX_START_BIT
            
		  // Wait i_Clk_per_bit-1 clock cycles for data bits to finish         
			TX_DATA_BITS :
				begin
					o_TX_Serial <= r_TX_Data[r_Bit_Index];
			  
					if (r_Clock_Count < i_Clk_per_bit-1) begin
						r_Clock_Count <= r_Clock_Count + 1;
						r_SM_Main     <= TX_DATA_BITS;
					end else begin
						r_Clock_Count <= 0;
					
						// Check if we have sent out all bits
						if (r_Bit_Index < 7) begin
							r_Bit_Index <= r_Bit_Index + 1;
							r_SM_Main   <= TX_DATA_BITS;
						end else begin
							r_Bit_Index <= 0;
							r_SM_Main   <= TX_STOP_BIT;
						end
					end 
				end // case: TX_DATA_BITS
		  
      
		  // Send out Stop bit.  Stop bit = 1
			TX_STOP_BIT :
				begin
					o_TX_Serial <= 1'b1;
			  
					// Wait i_Clk_per_bit-1 clock cycles for Stop bit to finish
					if (r_Clock_Count < i_Clk_per_bit-1) begin
						r_Clock_Count <= r_Clock_Count + 1;
						r_SM_Main     <= TX_STOP_BIT;
					end else begin
						o_TX_Done     <= 1'b1;
						r_Clock_Count <= 0;
						r_SM_Main     <= CLEANUP;
						//o_TX_Active   <= 1'b0;
					end 
				end // case: TX_STOP_BIT      
      
		  // Stay here 1 clock
			CLEANUP :
				begin
					o_TX_Done <= 1'b1;
					r_SM_Main <= IDLE;
					o_TX_Active_L   <= 1'b1;
				end		  
		  
			default :
				r_SM_Main <= IDLE;
      
		endcase
    end 
  end 
  
endmodule


module UART_RX
  (
   input            i_Rst_L,
   input            i_Clock,
   input            i_RX_Serial_asyn,
   input [11:0]		i_Clk_per_bit,	// clk_frequency / bit_rate
   output reg       o_RX_DV,		//flag Rx data valid in the output register
   output reg [7:0] o_RX_Byte
   );
   
  localparam IDLE         = 3'b000;
  localparam RX_START_BIT = 3'b001;
  localparam RX_DATA_BITS = 3'b010;
  localparam RX_STOP_BIT  = 3'b011;
  localparam CLEANUP      = 3'b100;
  
  reg [11:0] r_Clock_Count;
  reg [2:0] r_Bit_Index; //8 bits total
  reg [2:0] r_SM_Main;
    
  reg r_rx_meta;
  reg i_RX_Serial;
  
  reg [7:0] RX_Byte_temp;
  
  //Synchronize rx input
  always @(posedge i_Clock) begin	
	r_rx_meta <= i_RX_Serial_asyn;		
	i_RX_Serial <= r_rx_meta;
  end
  
  // Purpose: Control RX state machine
  always @(posedge i_Clock) begin
	if (i_Rst_L == 0) begin
		r_SM_Main <= 3'b000;
		o_RX_DV   <= 1'b0;
		o_RX_Byte <= 8'h00;
		RX_Byte_temp <= 8'h00;
    end else begin
		case (r_SM_Main)
			IDLE :
					begin
						o_RX_DV       <= 1'b0;
						r_Clock_Count <= 0;
						r_Bit_Index   <= 0;
				  
						if (i_RX_Serial == 1'b0) begin          // Start bit detected
							r_SM_Main <= RX_START_BIT;
						end else begin
							r_SM_Main <= IDLE;
						end
					end
		  
			// Check middle of start bit to make sure it's still low
			RX_START_BIT :
					begin
						if (r_Clock_Count == (i_Clk_per_bit-1)/2) begin
							if (i_RX_Serial == 1'b0) begin
								r_Clock_Count <= 0;  // reset counter, found the middle
								r_SM_Main <= RX_DATA_BITS;
							end else begin
								r_SM_Main <= IDLE;
							end
						end else begin
							r_Clock_Count <= r_Clock_Count + 1;
							r_SM_Main <= RX_START_BIT;
						end
					end 
		  
			// Wait i_Clk_per_bit-1 clock cycles to sample serial data
			RX_DATA_BITS :
					begin
						if (r_Clock_Count < i_Clk_per_bit-1) begin
							r_Clock_Count <= r_Clock_Count + 1;
							r_SM_Main <= RX_DATA_BITS;
						end else begin
							r_Clock_Count <= 0;
							RX_Byte_temp[r_Bit_Index] <= i_RX_Serial;
					
							// Check if we have received all bits
							if (r_Bit_Index < 7) begin
								r_Bit_Index <= r_Bit_Index + 1;
								r_SM_Main   <= RX_DATA_BITS;
							end else begin
								r_Bit_Index <= 0;
								r_SM_Main   <= RX_STOP_BIT;
								//o_RX_Byte <= RX_Byte_temp;
							end
						end
					end 
				
			// Receive Stop bit.  Stop bit = 1
			RX_STOP_BIT :
					begin
						// Wait i_Clk_per_bit-1 clock cycles for Stop bit to finish
						if (r_Clock_Count < i_Clk_per_bit-1) begin
							r_Clock_Count <= r_Clock_Count + 1;
							r_SM_Main     <= RX_STOP_BIT;
						end else begin
							o_RX_Byte <= RX_Byte_temp;
							o_RX_DV       <= 1'b1;  // Flag is high during 1 cycle
							r_Clock_Count <= 0;
							r_SM_Main     <= CLEANUP;
						end
					end 
		  		  
			// Stay here 1 clock
			CLEANUP :
					begin
						r_SM_Main <= IDLE;
						o_RX_DV   <= 1'b0;
					end
		  
			default :
					r_SM_Main <= IDLE;
		  
		endcase
    end 
  end 
  
endmodule // UART_RX

//This wrapper connects the UART_TX to the picorv32

module UART_TX_PICO (
	input rstn,
	input clk,	
	input [11:0] clk_per_bit,
	input [31:0] addr,
	input wen,
	input [7:0] wdata, //data to be transmited	
	input mem_valid,
	input mem_ready,
	output reg uart_tx_ready, //Acknowledge that address has been read
	output tx_uart,
	output uart_tx_int_flag //Active high when the module is IDLE (not transmitting)
);

parameter ADDR = 32'h0000_0000; // This address must be changed during instantiation!

wire start_tx;
assign start_tx = ((addr == ADDR) && mem_valid && wen)? 1'b1 : 1'b0;

always @(posedge clk) begin
	if (rstn == 0) begin
		uart_tx_ready <= 0;
	end else if (start_tx) begin
		uart_tx_ready <= (!mem_ready)? 1'b1 : 1'b0; 
	end else begin
		uart_tx_ready <= 1'b0;	
	end
end

UART_TX uart_transmitter(
	.i_Rst_L(rstn),
	.i_Clock(clk),
    .i_TX_DV(start_tx),		//control signal to start transmission
    .i_TX_Byte(wdata),
    .i_Clk_per_bit(clk_per_bit), // clk_frequency / bit_rate
    .o_TX_Active_L(uart_tx_int_flag), //output flag remains low during transmission and high when idle 
    .o_TX_Serial(tx_uart),
    .o_TX_Done()		
);

endmodule 

//This wrapper connects the UART_RX to the picorv32
module UART_RX_PICO (
	input rstn,
	input rx_uart,
	input clk,
	input [11:0] clk_per_bit,
	output [7:0] data_out,
	input [31:0] addr,		
	input ren,
	output uart_rx_int_flag, // 
	input mem_valid,
	input mem_ready,
	output reg uart_rx_ready //Acknowledge that address has been read
);
// ADDR must be passed during instantiation
parameter ADDR = 32'h00000000; 

always @(posedge clk) begin
	if (rstn == 0) begin
		uart_rx_ready <= 0;
	end else if (mem_valid && (addr == ADDR)) begin
		uart_rx_ready <= (!mem_ready)? 1'b1 : 1'b0;
	end
end

reg int_reset;
reg uart_rx_int_flag;

wire rx_ready;

UART_RX uart_receiver(
	  .i_Rst_L(rstn),
	  .i_Clock(clk),
	  .i_RX_Serial_asyn(rx),
	  .i_Clk_per_bit(clk_per_bit),
      .o_RX_DV(rx_ready),
      .o_RX_Byte(data_out)
   );

always @(posedge clk) begin
	if (rstn == 0) begin
		int_reset <= 0;			
		uart_rx_int_flag <= 0;
	end else begin
		if (addr == ADDR) begin
			if (ren) begin // The data has been read, the RX interrupt flg can be cleared
				int_reset <= 1;
			end
		end 
		
		if (int_reset) begin
			uart_rx_int_flag <= 0;
			int_reset <= 0;
		end else begin
			if (rx_ready) begin // raise RX interrupt flag
				uart_rx_int_flag <= 1;
			end
		end
		
	end
end

endmodule

`endif

picoRV32_rom/uart_tb.v
//uart_tb.v
`timescale 1ns/1ps

`include "uart.v"

`define CLK_FREQ 16000000
`define BRATE 9600
`define END_SIM 36000
`define RX_UART 32'hcafe_babe
`define TX_UART 32'hcaca_bebe

module uart_tb();

parameter N=`CLK_FREQ/`BRATE;

reg rstn;
reg clk;	
reg [11:0] clk_per_bit;
reg [31:0] addr;
reg wen;
reg [7:0] wdata; //data to be transmited	
reg mem_valid;
reg wstrobe;

//reg mem_ready;
wire mem_ready;

wire uart_tx_ready; //Acknowledge that address has been read
wire tx_uart;
wire uart_tx_int_flag;

wire [7:0] data_out;
wire uart_rx_int_flag;
wire uart_rx_ready;

assign mem_ready = uart_tx_ready || uart_rx_ready;

UART_TX_PICO #(.ADDR(`TX_UART)) tx(
	.rstn(rstn),
	.clk(clk),
	.clk_per_bit(clk_per_bit),
	.addr(addr),
	.wen(wstrobe),
	.wdata(wdata),
	.mem_valid(mem_valid),
	.mem_ready(mem_ready),
	.uart_tx_ready(uart_tx_ready),
	.tx_uart(tx_uart),
	.uart_tx_int_flag(uart_tx_int_flag)
);

UART_RX_PICO #(.ADDR(`RX_UART)) rx(
	.rstn(rstn),
	.rx_uart(tx_uart),
	.clk(clk),
	.clk_per_bit(clk_per_bit),	
	.addr(addr),		
	.ren(!wstrobe),	
	.mem_valid(mem_valid),
	.mem_ready(mem_ready),
	.data_out(data_out),
	.uart_rx_int_flag(uart_rx_int_flag), // 
	.uart_rx_ready(uart_rx_ready) //Acknowledge that address has been read
);


parameter tck = 62.5; // clock TinyFpga (1/16 MHz)
always #(tck/2) clk = ~clk;

initial begin
	$dumpfile("dump.vcd");
	$dumpvars(0,tx,rx);
	
	clk = 0;
	rstn = 1;
	wdata = 0;
	clk_per_bit = N;
	addr = 0;
	wstrobe = 0;
		
	#tck     rstn = 0;
	#(2*tck) rstn = 1;	
	
	#(3*tck) wdata = 8'haf;
	TXbyte;
	
	RXbyte;
	
	#(3*tck) wdata = 8'hee;
	TXbyte;
	
	RXbyte;
			 
	
	#(`END_SIM*tck) $finish;
end

task TXbyte;
	begin
		//#(3*tck) //wdata = 8'haf;
				 addr = `TX_UART;
				 mem_valid = 1;
				 wstrobe = 1;
		#(2*tck) wdata = 0;
				 addr = 0;
				 mem_valid = 0;
				 wstrobe = 0;
	end
endtask

task RXbyte;
	begin
		#((`END_SIM/2)*tck) addr = `RX_UART;
							mem_valid = 1;
							wstrobe = 0;
		#(2*tck) addr = 0;
				 mem_valid = 0;
				 wstrobe = 0;		
	end
endtask


endmodule

picoRV32_rom/dump.vcd
$date
	Thu Jun 25 10:55:10 2020
$end
$version
	Icarus Verilog
$end
$timescale
	1ps
$end
$scope module uart_tb $end
$scope module tx $end
$var wire 32 ! addr [31:0] $end
$var wire 1 " clk $end
$var wire 12 # clk_per_bit [11:0] $end
$var wire 1 $ mem_ready $end
$var wire 1 % mem_valid $end
$var wire 1 & rstn $end
$var wire 8 ' wdata [7:0] $end
$var wire 1 ( wen $end
$var wire 1 ) uart_tx_int_flag $end
$var wire 1 * tx_uart $end
$var wire 1 + start_tx $end
$var reg 1 , uart_tx_ready $end
$scope module uart_transmitter $end
$var wire 12 - i_Clk_per_bit [11:0] $end
$var wire 1 " i_Clock $end
$var wire 1 & i_Rst_L $end
$var wire 8 . i_TX_Byte [7:0] $end
$var wire 1 + i_TX_DV $end
$var reg 1 ) o_TX_Active_L $end
$var reg 1 / o_TX_Done $end
$var reg 1 * o_TX_Serial $end
$var reg 3 0 r_Bit_Index [2:0] $end
$var reg 12 1 r_Clock_Count [11:0] $end
$var reg 3 2 r_SM_Main [2:0] $end
$var reg 8 3 r_TX_Data [7:0] $end
$upscope $end
$upscope $end
$upscope $end
$scope module uart_tb $end
$scope module rx $end
$var wire 32 4 addr [31:0] $end
$var wire 1 " clk $end
$var wire 12 5 clk_per_bit [11:0] $end
$var wire 1 $ mem_ready $end
$var wire 1 % mem_valid $end
$var wire 1 6 ren $end
$var wire 1 & rstn $end
$var wire 1 * rx_uart $end
$var wire 1 7 rx_ready $end
$var wire 8 8 data_out [7:0] $end
$var reg 1 9 int_reset $end
$var reg 1 : uart_rx_int_flag $end
$var reg 1 ; uart_rx_ready $end
$scope module uart_receiver $end
$var wire 12 < i_Clk_per_bit [11:0] $end
$var wire 1 " i_Clock $end
$var wire 1 & i_Rst_L $end
$var wire 1 * i_RX_Serial_asyn $end
$var reg 8 = RX_Byte_temp [7:0] $end
$var reg 1 > i_RX_Serial $end
$var reg 8 ? o_RX_Byte [7:0] $end
$var reg 1 7 o_RX_DV $end
$var reg 3 @ r_Bit_Index [2:0] $end
$var reg 12 A r_Clock_Count [11:0] $end
$var reg 3 B r_SM_Main [2:0] $end
$var reg 1 C r_rx_meta $end
$upscope $end
$upscope $end
$upscope $end
$enddefinitions $end
#0
$dumpvars
xC
bx B
bx A
bx @
bx ?
x>
bx =
b11010000010 <
x;
x:
x9
bx 8
x7
16
b11010000010 5
b0 4
bx 3
bx 2
bx 1
bx 0
x/
b0 .
b11010000010 -
x,
0+
x*
x)
0(
b0 '
1&
x%
x$
b11010000010 #
0"
b0 !
$end
#31250
b0 2
0,
b0 B
1"
#62500
0"
0&
#93750
0$
0:
09
0;
b0 =
b0 8
b0 ?
07
1)
0/
1"
#125000
0"
#156250
1"
#187500
0"
1&
#218750
b0 @
b0 A
b0 0
b0 1
1*
1"
#250000
0"
#281250
1C
1"
#312500
0"
#343750
1>
1"
#375000
1+
0"
06
1(
1%
b11001010110010101011111010111110 !
b11001010110010101011111010111110 4
b10101111 '
b10101111 .
#406250
1$
b1 2
b10101111 3
0)
1,
1"
#437500
0"
#468750
0$
0,
b1 1
0*
1"
#500000
0+
0"
16
0(
0%
b0 !
b0 4
b0 '
b0 .
#531250
b10 1
0C
1"
#562500
0"
#593750
0>
b11 1
1"
#625000
0"
#656250
b100 1
b1 B
1"
#687500
0"
#718750
b1 A
b101 1
1"
#750000
0"
#781250
b110 1
b10 A
1"
#812500
0"
#843750
b11 A
b111 1
1"
#875000
0"
#906250
b1000 1
b100 A
1"
#937500
0"
#968750
b101 A
b1001 1
1"
#1000000
0"
#1031250
b1010 1
b110 A
1"
#1062500
0"
#1093750
b111 A
b1011 1
1"
#1125000
0"
#1156250
b1100 1
b1000 A
1"
#1187500
0"
#1218750
b1001 A
b1101 1
1"
#1250000
0"
#1281250
b1110 1
b1010 A
1"
#1312500
0"
#1343750
b1011 A
b1111 1
1"
#1375000
0"
#1406250
b10000 1
b1100 A
1"
#1437500
0"
#1468750
b1101 A
b10001 1
1"
#1500000
0"
#1531250
b10010 1
b1110 A
1"
#1562500
0"
#1593750
b1111 A
b10011 1
1"
#1625000
0"
#1656250
b10100 1
b10000 A
1"
#1687500
0"
#1718750
b10001 A
b10101 1
1"
#1750000
0"
#1781250
b10110 1
b10010 A
1"
#1812500
0"
#1843750
b10011 A
b10111 1
1"
#1875000
0"
#1906250
b11000 1
b10100 A
1"
#1937500
0"
#1968750
b10101 A
b11001 1
1"
#2000000
0"
#2031250
b11010 1
b10110 A
1"
#2062500
0"
#2093750
b10111 A
b11011 1
1"
#2125000
0"
#2156250
b11100 1
b11000 A
1"
#2187500
0"
#2218750
b11001 A
b11101 1
1"
#2250000
0"
#2281250
b11110 1
b11010 A
1"
#2312500
0"
#2343750
b11011 A
b11111 1
1"
#2375000
0"
#2406250
b100000 1
b11100 A
1"
#2437500
0"
#2468750
b11101 A
b100001 1
1"
#2500000
0"
#2531250
b100010 1
b11110 A
1"
#2562500
0"
#2593750
b11111 A
b100011 1
1"
#2625000
0"
#2656250
b100100 1
b100000 A
1"
#2687500
0"
#2718750
b100001 A
b100101 1
1"
#2750000
0"
#2781250
b100110 1
b100010 A
1"
#2812500
0"
#2843750
b100011 A
b100111 1
1"
#2875000
0"
#2906250
b101000 1
b100100 A
1"
#2937500
0"
#2968750
b100101 A
b101001 1
1"
#3000000
0"
#3031250
b101010 1
b100110 A
1"
#3062500
0"
#3093750
b100111 A
b101011 1
1"
#3125000
0"
#3156250
b101100 1
b101000 A
1"
#3187500
0"
#3218750
b101001 A
b101101 1
1"
#3250000
0"
#3281250
b101110 1
b101010 A
1"
#3312500
0"
#3343750
b101011 A
b101111 1
1"
#3375000
0"
#3406250
b110000 1
b101100 A
1"
#3437500
0"
#3468750
b101101 A
b110001 1
1"
#3500000
0"
#3531250
b110010 1
b101110 A
1"
#3562500
0"
#3593750
b101111 A
b110011 1
1"
#3625000
0"
#3656250
b110100 1
b110000 A
1"
#3687500
0"
#3718750
b110001 A
b110101 1
1"
#3750000
0"
#3781250
b110110 1
b110010 A
1"
#3812500
0"
#3843750
b110011 A
b110111 1
1"
#3875000
0"
#3906250
b111000 1
b110100 A
1"
#3937500
0"
#3968750
b110101 A
b111001 1
1"
#4000000
0"
#4031250
b111010 1
b110110 A
1"
#4062500
0"
#4093750
b110111 A
b111011 1
1"
#4125000
0"
#4156250
b111100 1
b111000 A
1"
#4187500
0"
#4218750
b111001 A
b111101 1
1"
#4250000
0"
#4281250
b111110 1
b111010 A
1"
#4312500
0"
#4343750
b111011 A
b111111 1
1"
#4375000
0"
#4406250
b1000000 1
b111100 A
1"
#4437500
0"
#4468750
b111101 A
b1000001 1
1"
#4500000
0"
#4531250
b1000010 1
b111110 A
1"
#4562500
0"
#4593750
b111111 A
b1000011 1
1"
#4625000
0"
#4656250
b1000100 1
b1000000 A
1"
#4687500
0"
#4718750
b1000001 A
b1000101 1
1"
#4750000
0"
#4781250
b1000110 1
b1000010 A
1"
#4812500
0"
#4843750
b1000011 A
b1000111 1
1"
#4875000
0"
#4906250
b1001000 1
b1000100 A
1"
#4937500
0"
#4968750
b1000101 A
b1001001 1
1"
#5000000
0"
#5031250
b1001010 1
b1000110 A
1"
#5062500
0"
#5093750
b1000111 A
b1001011 1
1"
#5125000
0"
#5156250
b1001100 1
b1001000 A
1"
#5187500
0"
#5218750
b1001001 A
b1001101 1
1"
#5250000
0"
#5281250
b1001110 1
b1001010 A
1"
#5312500
0"
#5343750
b1001011 A
b1001111 1
1"
#5375000
0"
#5406250
b1010000 1
b1001100 A
1"
#5437500
0"
#5468750
b1001101 A
b1010001 1
1"
#5500000
0"
#5531250
b1010010 1
b1001110 A
1"
#5562500
0"
#5593750
b1001111 A
b1010011 1
1"
#5625000
0"
#5656250
b1010100 1
b1010000 A
1"
#5687500
0"
#5718750
b1010001 A
b1010101 1
1"
#5750000
0"
#5781250
b1010110 1
b1010010 A
1"
#5812500
0"
#5843750
b1010011 A
b1010111 1
1"
#5875000
0"
#5906250
b1011000 1
b1010100 A
1"
#5937500
0"
#5968750
b1010101 A
b1011001 1
1"
#6000000
0"
#6031250
b1011010 1
b1010110 A
1"
#6062500
0"
#6093750
b1010111 A
b1011011 1
1"
#6125000
0"
#6156250
b1011100 1
b1011000 A
1"
#6187500
0"
#6218750
b1011001 A
b1011101 1
1"
#6250000
0"
#6281250
b1011110 1
b1011010 A
1"
#6312500
0"
#6343750
b1011011 A
b1011111 1
1"
#6375000
0"
#6406250
b1100000 1
b1011100 A
1"
#6437500
0"
#6468750
b1011101 A
b1100001 1
1"
#6500000
0"
#6531250
b1100010 1
b1011110 A
1"
#6562500
0"
#6593750
b1011111 A
b1100011 1
1"
#6625000
0"
#6656250
b1100100 1
b1100000 A
1"
#6687500
0"
#6718750
b1100001 A
b1100101 1
1"
#6750000
0"
#6781250
b1100110 1
b1100010 A
1"
#6812500
0"
#6843750
b1100011 A
b1100111 1
1"
#6875000
0"
#6906250
b1101000 1
b1100100 A
1"
#6937500
0"
#6968750
b1100101 A
b1101001 1
1"
#7000000
0"
#7031250
b1101010 1
b1100110 A
1"
#7062500
0"
#7093750
b1100111 A
b1101011 1
1"
#7125000
0"
#7156250
b1101100 1
b1101000 A
1"
#7187500
0"
#7218750
b1101001 A
b1101101 1
1"
#7250000
0"
#7281250
b1101110 1
b1101010 A
1"
#7312500
0"
#7343750
b1101011 A
b1101111 1
1"
#7375000
0"
#7406250
b1110000 1
b1101100 A
1"
#7437500
0"
#7468750
b1101101 A
b1110001 1
1"
#7500000
0"
#7531250
b1110010 1
b1101110 A
1"
#7562500
0"
#7593750
b1101111 A
b1110011 1
1"
#7625000
0"
#7656250
b1110100 1
b1110000 A
1"
#7687500
0"
#7718750
b1110001 A
b1110101 1
1"
#7750000
0"
#7781250
b1110110 1
b1110010 A
1"
#7812500
0"
#7843750
b1110011 A
b1110111 1
1"
#7875000
0"
#7906250
b1111000 1
b1110100 A
1"
#7937500
0"
#7968750
b1110101 A
b1111001 1
1"
#8000000
0"
#8031250
b1111010 1
b1110110 A
1"
#8062500
0"
#8093750
b1110111 A
b1111011 1
1"
#8125000
0"
#8156250
b1111100 1
b1111000 A
1"
#8187500
0"
#8218750
b1111001 A
b1111101 1
1"
#8250000
0"
#8281250
b1111110 1
b1111010 A
1"
#8312500
0"
#8343750
b1111011 A
b1111111 1
1"
#8375000
0"
#8406250
b10000000 1
b1111100 A
1"
#8437500
0"
#8468750
b1111101 A
b10000001 1
1"
#8500000
0"
#8531250
b10000010 1
b1111110 A
1"
#8562500
0"
#8593750
b1111111 A
b10000011 1
1"
#8625000
0"
#8656250
b10000100 1
b10000000 A
1"
#8687500
0"
#8718750
b10000001 A
b10000101 1
1"
#8750000
0"
#8781250
b10000110 1
b10000010 A
1"
#8812500
0"
#8843750
b10000011 A
b10000111 1
1"
#8875000
0"
#8906250
b10001000 1
b10000100 A
1"
#8937500
0"
#8968750
b10000101 A
b10001001 1
1"
#9000000
0"
#9031250
b10001010 1
b10000110 A
1"
#9062500
0"
#9093750
b10000111 A
b10001011 1
1"
#9125000
0"
#9156250
b10001100 1
b10001000 A
1"
#9187500
0"
#9218750
b10001001 A
b10001101 1
1"
#9250000
0"
#9281250
b10001110 1
b10001010 A
1"
#9312500
0"
#9343750
b10001011 A
b10001111 1
1"
#9375000
0"
#9406250
b10010000 1
b10001100 A
1"
#9437500
0"
#9468750
b10001101 A
b10010001 1
1"
#9500000
0"
#9531250
b10010010 1
b10001110 A
1"
#9562500
0"
#9593750
b10001111 A
b10010011 1
1"
#9625000
0"
#9656250
b10010100 1
b10010000 A
1"
#9687500
0"
#9718750
b10010001 A
b10010101 1
1"
#9750000
0"
#9781250
b10010110 1
b10010010 A
1"
#9812500
0"
#9843750
b10010011 A
b10010111 1
1"
#9875000
0"
#9906250
b10011000 1
b10010100 A
1"
#9937500
0"
#9968750
b10010101 A
b10011001 1
1"
#10000000
0"
#10031250
b10011010 1
b10010110 A
1"
#10062500
0"
#10093750
b10010111 A
b10011011 1
1"
#10125000
0"
#10156250
b10011100 1
b10011000 A
1"
#10187500
0"
#10218750
b10011001 A
b10011101 1
1"
#10250000
0"
#10281250
b10011110 1
b10011010 A
1"
#10312500
0"
#10343750
b10011011 A
b10011111 1
1"
#10375000
0"
#10406250
b10100000 1
b10011100 A
1"
#10437500
0"
#10468750
b10011101 A
b10100001 1
1"
#10500000
0"
#10531250
b10100010 1
b10011110 A
1"
#10562500
0"
#10593750
b10011111 A
b10100011 1
1"
#10625000
0"
#10656250
b10100100 1
b10100000 A
1"
#10687500
0"
#10718750
b10100001 A
b10100101 1
1"
#10750000
0"
#10781250
b10100110 1
b10100010 A
1"
#10812500
0"
#10843750
b10100011 A
b10100111 1
1"
#10875000
0"
#10906250
b10101000 1
b10100100 A
1"
#10937500
0"
#10968750
b10100101 A
b10101001 1
1"
#11000000
0"
#11031250
b10101010 1
b10100110 A
1"
#11062500
0"
#11093750
b10100111 A
b10101011 1
1"
#11125000
0"
#11156250
b10101100 1
b10101000 A
1"
#11187500
0"
#11218750
b10101001 A
b10101101 1
1"
#11250000
0"
#11281250
b10101110 1
b10101010 A
1"
#11312500
0"
#11343750
b10101011 A
b10101111 1
1"
#11375000
0"
#11406250
b10110000 1
b10101100 A
1"
#11437500
0"
#11468750
b10101101 A
b10110001 1
1"
#11500000
0"
#11531250
b10110010 1
b10101110 A
1"
#11562500
0"
#11593750
b10101111 A
b10110011 1
1"
#11625000
0"
#11656250
b10110100 1
b10110000 A
1"
#11687500
0"
#11718750
b10110001 A
b10110101 1
1"
#11750000
0"
#11781250
b10110110 1
b10110010 A
1"
#11812500
0"
#11843750
b10110011 A
b10110111 1
1"
#11875000
0"
#11906250
b10111000 1
b10110100 A
1"
#11937500
0"
#11968750
b10110101 A
b10111001 1
1"
#12000000
0"
#12031250
b10111010 1
b10110110 A
1"
#12062500
0"
#12093750
b10110111 A
b10111011 1
1"
#12125000
0"
#12156250
b10111100 1
b10111000 A
1"
#12187500
0"
#12218750
b10111001 A
b10111101 1
1"
#12250000
0"
#12281250
b10111110 1
b10111010 A
1"
#12312500
0"
#12343750
b10111011 A
b10111111 1
1"
#12375000
0"
#12406250
b11000000 1
b10111100 A
1"
#12437500
0"
#12468750
b10111101 A
b11000001 1
1"
#12500000
0"
#12531250
b11000010 1
b10111110 A
1"
#12562500
0"
#12593750
b10111111 A
b11000011 1
1"
#12625000
0"
#12656250
b11000100 1
b11000000 A
1"
#12687500
0"
#12718750
b11000001 A
b11000101 1
1"
#12750000
0"
#12781250
b11000110 1
b11000010 A
1"
#12812500
0"
#12843750
b11000011 A
b11000111 1
1"
#12875000
0"
#12906250
b11001000 1
b11000100 A
1"
#12937500
0"
#12968750
b11000101 A
b11001001 1
1"
#13000000
0"
#13031250
b11001010 1
b11000110 A
1"
#13062500
0"
#13093750
b11000111 A
b11001011 1
1"
#13125000
0"
#13156250
b11001100 1
b11001000 A
1"
#13187500
0"
#13218750
b11001001 A
b11001101 1
1"
#13250000
0"
#13281250
b11001110 1
b11001010 A
1"
#13312500
0"
#13343750
b11001011 A
b11001111 1
1"
#13375000
0"
#13406250
b11010000 1
b11001100 A
1"
#13437500
0"
#13468750
b11001101 A
b11010001 1
1"
#13500000
0"
#13531250
b11010010 1
b11001110 A
1"
#13562500
0"
#13593750
b11001111 A
b11010011 1
1"
#13625000
0"
#13656250
b11010100 1
b11010000 A
1"
#13687500
0"
#13718750
b11010001 A
b11010101 1
1"
#13750000
0"
#13781250
b11010110 1
b11010010 A
1"
#13812500
0"
#13843750
b11010011 A
b11010111 1
1"
#13875000
0"
#13906250
b11011000 1
b11010100 A
1"
#13937500
0"
#13968750
b11010101 A
b11011001 1
1"
#14000000
0"
#14031250
b11011010 1
b11010110 A
1"
#14062500
0"
#14093750
b11010111 A
b11011011 1
1"
#14125000
0"
#14156250
b11011100 1
b11011000 A
1"
#14187500
0"
#14218750
b11011001 A
b11011101 1
1"
#14250000
0"
#14281250
b11011110 1
b11011010 A
1"
#14312500
0"
#14343750
b11011011 A
b11011111 1
1"
#14375000
0"
#14406250
b11100000 1
b11011100 A
1"
#14437500
0"
#14468750
b11011101 A
b11100001 1
1"
#14500000
0"
#14531250
b11100010 1
b11011110 A
1"
#14562500
0"
#14593750
b11011111 A
b11100011 1
1"
#14625000
0"
#14656250
b11100100 1
b11100000 A
1"
#14687500
0"
#14718750
b11100001 A
b11100101 1
1"
#14750000
0"
#14781250
b11100110 1
b11100010 A
1"
#14812500
0"
#14843750
b11100011 A
b11100111 1
1"
#14875000
0"
#14906250
b11101000 1
b11100100 A
1"
#14937500
0"
#14968750
b11100101 A
b11101001 1
1"
#15000000
0"
#15031250
b11101010 1
b11100110 A
1"
#15062500
0"
#15093750
b11100111 A
b11101011 1
1"
#15125000
0"
#15156250
b11101100 1
b11101000 A
1"
#15187500
0"
#15218750
b11101001 A
b11101101 1
1"
#15250000
0"
#15281250
b11101110 1
b11101010 A
1"
#15312500
0"
#15343750
b11101011 A
b11101111 1
1"
#15375000
0"
#15406250
b11110000 1
b11101100 A
1"
#15437500
0"
#15468750
b11101101 A
b11110001 1
1"
#15500000
0"
#15531250
b11110010 1
b11101110 A
1"
#15562500
0"
#15593750
b11101111 A
b11110011 1
1"
#15625000
0"
#15656250
b11110100 1
b11110000 A
1"
#15687500
0"
#15718750
b11110001 A
b11110101 1
1"
#15750000
0"
#15781250
b11110110 1
b11110010 A
1"
#15812500
0"
#15843750
b11110011 A
b11110111 1
1"
#15875000
0"
#15906250
b11111000 1
b11110100 A
1"
#15937500
0"
#15968750
b11110101 A
b11111001 1
1"
#16000000
0"
#16031250
b11111010 1
b11110110 A
1"
#16062500
0"
#16093750
b11110111 A
b11111011 1
1"
#16125000
0"
#16156250
b11111100 1
b11111000 A
1"
#16187500
0"
#16218750
b11111001 A
b11111101 1
1"
#16250000
0"
#16281250
b11111110 1
b11111010 A
1"
#16312500
0"
