spi_master/SPI_Master.v
///////////////////////////////////////////////////////////////////////////////
// Description: SPI (Serial Peripheral Interface) Master
//              Creates master based on input configuration.
//              Sends a byte one bit at a time on MOSI
//              Will also receive byte data one bit at a time on MISO.
//              Any data on input byte will be shipped out on MOSI.
//
//              To kick-off transaction, user must pulse i_TX_DV.
//              This module supports multi-byte transmissions by pulsing
//              i_TX_DV and loading up i_TX_Byte when o_TX_Ready is high.
//
//              This module is only responsible for controlling Clk, MOSI, 
//              and MISO.  If the SPI peripheral requires a chip-select, 
//              this must be done at a higher level.
//
// Note:        i_Clk must be at least 2x faster than i_SPI_Clk
//
// Parameters:  SPI_MODE, can be 0, 1, 2, or 3.  See above.
//              Can be configured in one of 4 modes:
//              Mode | Clock Polarity (CPOL/CKP) | Clock Phase (CPHA)
//               0   |             0             |        0
//               1   |             0             |        1
//               2   |             1             |        0
//               3   |             1             |        1
//              More: https://en.wikipedia.org/wiki/Serial_Peripheral_Interface_Bus#Mode_numbers
//              CLKS_PER_HALF_BIT - Sets frequency of o_SPI_Clk.  o_SPI_Clk is
//              derived from i_Clk.  Set to integer number of clocks for each
//              half-bit of SPI data.  E.g. 100 MHz i_Clk, CLKS_PER_HALF_BIT = 2
//              would create o_SPI_CLK of 25 MHz.  Must be >= 2
//
///////////////////////////////////////////////////////////////////////////////

module SPI_Master
  #(parameter SPI_MODE = 0)   
  (
   // Control/Data Signals,
   input        i_Rst_L,     // FPGA Reset
   input        i_Clk,       // FPGA Clock
   
   // SPI frequency configuration   
   input [11:0]	i_Clks_per_half_bit,	
   
   // TX (MOSI) Signals
   input [7:0]  i_TX_Byte,        // Byte to transmit on MOSI
   input        i_TX_DV,          // Data Valid Pulse with i_TX_Byte
   output reg   o_TX_Ready,       // Transmit Ready for next byte
   
   // RX (MISO) Signals
   output reg       o_RX_DV,     // Data Valid pulse (1 clock cycle)
   output reg [7:0] o_RX_Byte,   // Byte received on MISO

   // SPI Interface
   output reg o_SPI_Clk,
   input      i_SPI_MISO,
   output reg o_SPI_MOSI
   );

  // SPI Interface (All Runs at SPI Clock Domain)
  wire w_CPOL;     // Clock polarity
  wire w_CPHA;     // Clock phase
  
  reg [11:0] r_SPI_Clk_Count;	
  reg r_SPI_Clk;
  reg [4:0] r_SPI_Clk_Edges;
  reg r_Leading_Edge;
  reg r_Trailing_Edge;
  reg       r_TX_DV;
  reg [7:0] r_TX_Byte;

  reg [2:0] r_RX_Bit_Count;
  reg [2:0] r_TX_Bit_Count;

  // CPOL: Clock Polarity
  // CPOL=0 means clock idles at 0, leading edge is rising edge.
  // CPOL=1 means clock idles at 1, leading edge is falling edge.
  assign w_CPOL  = (SPI_MODE == 2) | (SPI_MODE == 3);

  // CPHA: Clock Phase
  // CPHA=0 means the "out" side changes the data on trailing edge of clock
  //              the "in" side captures data on leading edge of clock
  // CPHA=1 means the "out" side changes the data on leading edge of clock
  //              the "in" side captures data on the trailing edge of clock
  assign w_CPHA  = (SPI_MODE == 1) | (SPI_MODE == 3);

  // Purpose: Generate SPI Clock correct number of times when DV pulse comes
  always @(posedge i_Clk) begin
    if (i_Rst_L == 0) begin
      o_TX_Ready      <= 1'b0;
      r_SPI_Clk_Edges <= 0;
      r_Leading_Edge  <= 1'b0;
      r_Trailing_Edge <= 1'b0;
      r_SPI_Clk       <= w_CPOL; // assign default state to idle state
      r_SPI_Clk_Count <= 0;
    end else begin
    	
      // Default assignments
      r_Leading_Edge  <= 1'b0;
      r_Trailing_Edge <= 1'b0;
      
      if (i_TX_DV) begin
        o_TX_Ready      <= 1'b0;
        r_SPI_Clk_Edges <= 16;  // Total # edges in one byte ALWAYS 16
      end else if (r_SPI_Clk_Edges > 0) begin
        o_TX_Ready <= 1'b0;
        
        if (r_SPI_Clk_Count == i_Clks_per_half_bit*2-1) begin
          r_SPI_Clk_Edges <= r_SPI_Clk_Edges - 1;
          r_Trailing_Edge <= 1'b1;
          r_SPI_Clk_Count <= 0;
          r_SPI_Clk       <= ~r_SPI_Clk;
        end else if (r_SPI_Clk_Count == i_Clks_per_half_bit-1) begin
          r_SPI_Clk_Edges <= r_SPI_Clk_Edges - 1;
          r_Leading_Edge  <= 1'b1;
          r_SPI_Clk_Count <= r_SPI_Clk_Count + 1;
          r_SPI_Clk       <= ~r_SPI_Clk;
        end else begin
          r_SPI_Clk_Count <= r_SPI_Clk_Count + 1;
        end
      end else begin
        o_TX_Ready <= 1'b1;
      end     
      
    end // else: !if(~i_Rst_L)
  end // always @ (posedge i_Clk or negedge i_Rst_L)


  // Purpose: Register i_TX_Byte when Data Valid is pulsed.
  // Keeps local storage of byte in case higher level module changes the data
  always @(posedge i_Clk) begin
    if (i_Rst_L == 0) begin
      r_TX_Byte <= 8'h00;
      r_TX_DV   <= 1'b0;
    end else begin
        r_TX_DV <= i_TX_DV; // 1 clock cycle delay
        if (i_TX_DV) begin
          r_TX_Byte <= i_TX_Byte;
        end
    end // else: !if(~i_Rst_L)
  end // always @ (posedge i_Clk or negedge i_Rst_L)

  
  // Purpose: Generate MOSI data
  // Works with both CPHA=0 and CPHA=1
  always @(posedge i_Clk) begin
    if (i_Rst_L == 0) begin
      o_SPI_MOSI     <= 1'b0;
      r_TX_Bit_Count <= 3'b111; // send MSb first
    end else begin
      // If ready is high, reset bit counts to default
      if (o_TX_Ready) begin
        r_TX_Bit_Count <= 3'b111;
      end
      // Catch the case where we start transaction and CPHA = 0
      else if (r_TX_DV & ~w_CPHA) begin
        o_SPI_MOSI     <= r_TX_Byte[3'b111];
        r_TX_Bit_Count <= 3'b110;
      end else if ((r_Leading_Edge & w_CPHA) | (r_Trailing_Edge & ~w_CPHA)) begin
        r_TX_Bit_Count <= r_TX_Bit_Count - 1;
        o_SPI_MOSI     <= r_TX_Byte[r_TX_Bit_Count];
      end
    end
  end


  // Purpose: Read in MISO data.
  always @(posedge i_Clk) begin 
  	if (i_Rst_L == 0) begin
      o_RX_Byte      <= 8'h00;
      o_RX_DV        <= 1'b0;
      r_RX_Bit_Count <= 3'b111;
  	end else begin

      // Default Assignments
      o_RX_DV   <= 1'b0;

      if (o_TX_Ready) begin // Check if ready is high, if so reset bit count to default      
        r_RX_Bit_Count <= 3'b111;
      end else if ((r_Leading_Edge & ~w_CPHA) | (r_Trailing_Edge & w_CPHA)) begin
        o_RX_Byte[r_RX_Bit_Count] <= i_SPI_MISO;  // Sample data
        r_RX_Bit_Count            <= r_RX_Bit_Count - 1;
        if (r_RX_Bit_Count == 3'b000) begin
          o_RX_DV   <= 1'b1;   // Byte done, pulse Data Valid
        end
      end
    end
  end
    
  // Purpose: Add clock delay to signals for alignment.
  always @(posedge i_Clk)
  begin
    if (i_Rst_L == 0) begin
      o_SPI_Clk  <= w_CPOL;
    end else begin
        o_SPI_Clk <= r_SPI_Clk;
    end // else: !if(~i_Rst_L)
  end // always @ (posedge i_Clk or negedge i_Rst_L)
  
endmodule // SPI_Master

module SPI_Master_Pico (
	input rstn,
	input clk,
	input [11:0] Clks_per_half_bit,	
	input [31:0] addr,
	input wen,
	input [7:0] wdata, //data to be transmited	
	input mem_valid,
	input mem_ready,
	output reg spi_master_ready, //Aknowledge that address has been read
	output spi_master_tx_int_flag,	
	output [7:0] rx_data,	
	output SPI_Clk,
	input  SPI_MISO,
	output SPI_MOSI
);
	
parameter ADDR = 32'h0000_0000; // This address must be changed during instantiation!
	
wire start_spi;
assign start_spi = ((addr == ADDR) && mem_valid && wen)? 1'b1 : 1'b0;
	
always @(posedge clk) begin
	if (rstn == 0) begin
		spi_master_ready <= 0;
	end else if (start_spi) begin
		spi_master_ready <= (!mem_ready)? 1'b1 : 1'b0;
	end else begin
		spi_master_ready <= 1'b0;
	end
end

SPI_Master #(.SPI_MODE(0)) spi_master (
	.i_Rst_L(rstn),     // FPGA Reset
	.i_Clk(clk),       // FPGA Clock
	.i_Clks_per_half_bit(Clks_per_half_bit),	
	.i_TX_Byte(wdata),        // Byte to transmit on MOSI
	.i_TX_DV(start_spi),          // Data Valid Pulse with i_TX_Byte
	.o_TX_Ready(spi_master_tx_int_flag),       // Transmit Ready for next byte
	.o_RX_DV(),     // Data Valid pulse (1 clock cycle)
	.o_RX_Byte(rx_data),   // Byte received on MISO
	.o_SPI_Clk(SPI_Clk),
	.i_SPI_MISO(SPI_MISO),
	.o_SPI_MOSI(SPI_MOSI)
);	
	
endmodule

spi_master/SPI_Master_Pico_TB.sv
///////////////////////////////////////////////////////////////////////////////
// Description:       Simple test bench for SPI Master module
///////////////////////////////////////////////////////////////////////////////
`timescale 1ns/1ps

`include "SPI_Master.v"

`define CLK_FREQ 16000000
`define SPI_FREQ 1600000
`define SPI_MASTER 32'hcaca_bebe

module SPI_Master_Pico_TB ();
  
  //parameter SPI_MODE = 0; // CPOL = 0, CPHA = 0
    
  parameter CLKS_PER_HALF_BIT = (`CLK_FREQ/`SPI_FREQ)/2;
  parameter CLK_PERIOD = 62.5;  // Period Clock TinyFpga 1/16 MHz

  logic rstn = 1'b0;
  logic clk = 1'b0;
  logic [11:0] Clks_per_half_bit = CLKS_PER_HALF_BIT;
  logic [31:0] addr = 0;
  logic wstrobe = 0;
  logic [7:0] wdata = 0; //data to be transmited	
  logic mem_valid = 0;
  logic mem_ready;
  logic spi_master_ready; //Aknowledge that address has been read
  logic spi_master_tx_int_flag;	
  logic [7:0] rx_data;
  logic SPI_Clk;
  //logic SPI_MISO;
  logic SPI_MOSI;

  assign mem_ready = spi_master_ready; 
  
  SPI_Master_Pico #(.ADDR(`SPI_MASTER)) spi(
  	.rstn(rstn),
  	.clk(clk),
  	.Clks_per_half_bit(Clks_per_half_bit),
  	.addr(addr),
  	.wen(wstrobe),
  	.wdata(wdata), //data to be transmited	
  	.mem_valid(mem_valid),
  	.mem_ready(mem_ready),
  	.spi_master_ready(spi_master_ready), //Aknowledge that address has been read
  	.spi_master_tx_int_flag(spi_master_tx_int_flag),	
  	.rx_data(rx_data),	
  	.SPI_Clk(SPI_Clk),
  	.SPI_MISO(SPI_MOSI),
  	.SPI_MOSI(SPI_MOSI) //Back to back test
  );
  
  // Clock Generator:
  always #(CLK_PERIOD) clk = ~clk;

  // Sends a single byte from master.
  task SendSingleByte(input [7:0] data);
    @(posedge clk);
     wdata <= data;
   	 addr <= `SPI_MASTER;
   	 mem_valid <= 1;
   	 wstrobe <= 1;
    
    @(posedge clk);
     wdata <= 0;
     addr <= 0;
     mem_valid <= 0;
     wstrobe <= 1'b0;
    @(posedge spi_master_tx_int_flag);
     //repeat(100) @(posedge clk);
  endtask // SendSingleByte

  
  initial
    begin
      // Required for EDA Playground
      $dumpfile("dump.vcd"); 
      $dumpvars;
      
      repeat(10) @(posedge clk);
      rstn = 1'b0;
      repeat(10) @(posedge clk);
      rstn = 1'b1;
      repeat(10) @(posedge clk);
      
      // Test single byte
      SendSingleByte(8'hC1);
      $display("Sent out 0xC1, Received 0x%X", rx_data); 
      
      // Test double byte
      SendSingleByte(8'hBE);
      $display("Sent out 0xBE, Received 0x%X", rx_data); 
      SendSingleByte(8'hEF);
      $display("Sent out 0xEF, Received 0x%X", rx_data); 
      repeat(100) @(posedge clk);
      $finish();      
    end // initial begin

endmodule // SPI_Slave

spi_master/dump.vcd
$date
	Tue Nov 10 15:15:27 2020
$end
$version
	Icarus Verilog
$end
$timescale
	1ps
$end
$scope module SPI_Master_Pico_TB $end
$var wire 1 ! mem_ready $end
$var wire 1 " spi_master_tx_int_flag $end
$var wire 1 # spi_master_ready $end
$var wire 8 $ rx_data [7:0] $end
$var wire 1 % SPI_MOSI $end
$var wire 1 & SPI_Clk $end
$var reg 12 ' Clks_per_half_bit [11:0] $end
$var reg 32 ( addr [31:0] $end
$var reg 1 ) clk $end
$var reg 1 * mem_valid $end
$var reg 1 + rstn $end
$var reg 8 , wdata [7:0] $end
$var reg 1 - wstrobe $end
$scope module spi $end
$var wire 12 . Clks_per_half_bit [11:0] $end
$var wire 32 / addr [31:0] $end
$var wire 1 ) clk $end
$var wire 1 ! mem_ready $end
$var wire 1 * mem_valid $end
$var wire 1 + rstn $end
$var wire 8 0 wdata [7:0] $end
$var wire 1 - wen $end
$var wire 1 1 start_spi $end
$var wire 1 " spi_master_tx_int_flag $end
$var wire 8 2 rx_data [7:0] $end
$var wire 1 % SPI_MOSI $end
$var wire 1 % SPI_MISO $end
$var wire 1 & SPI_Clk $end
$var reg 1 # spi_master_ready $end
$scope module spi_master $end
$var wire 1 ) i_Clk $end
$var wire 12 3 i_Clks_per_half_bit [11:0] $end
$var wire 1 + i_Rst_L $end
$var wire 8 4 i_TX_Byte [7:0] $end
$var wire 1 1 i_TX_DV $end
$var wire 1 5 w_CPHA $end
$var wire 1 6 w_CPOL $end
$var wire 1 % i_SPI_MISO $end
$var reg 8 7 o_RX_Byte [7:0] $end
$var reg 1 8 o_RX_DV $end
$var reg 1 & o_SPI_Clk $end
$var reg 1 % o_SPI_MOSI $end
$var reg 1 " o_TX_Ready $end
$var reg 1 9 r_Leading_Edge $end
$var reg 3 : r_RX_Bit_Count [2:0] $end
$var reg 1 ; r_SPI_Clk $end
$var reg 12 < r_SPI_Clk_Count [11:0] $end
$var reg 5 = r_SPI_Clk_Edges [4:0] $end
$var reg 3 > r_TX_Bit_Count [2:0] $end
$var reg 8 ? r_TX_Byte [7:0] $end
$var reg 1 @ r_TX_DV $end
$var reg 1 A r_Trailing_Edge $end
$upscope $end
$upscope $end
$scope task SendSingleByte $end
$var reg 8 B data [7:0] $end
$upscope $end
$upscope $end
$enddefinitions $end
#0
$dumpvars
bx B
xA
x@
bx ?
bx >
bx =
bx <
x;
bx :
x9
x8
bx 7
06
05
b0 4
b101 3
bx 2
01
b0 0
b0 /
b101 .
0-
b0 ,
0+
0*
0)
b0 (
b101 '
x&
x%
bx $
x#
x"
x!
$end
#62500
b0 <
0;
0A
09
b0 =
0"
0@
b0 ?
b111 >
0%
b111 :
08
b0 $
b0 2
b0 7
0&
0!
0#
1)
#125000
0)
#187500
1)
#250000
0)
#312500
1)
#375000
0)
#437500
1)
#500000
0)
#562500
1)
#625000
0)
#687500
1)
#750000
0)
#812500
1)
#875000
0)
#937500
1)
#1000000
0)
#1062500
1)
#1125000
0)
#1187500
1)
#1250000
0)
#1312500
1)
#1375000
0)
#1437500
1)
#1500000
0)
#1562500
1)
#1625000
0)
#1687500
1)
#1750000
0)
#1812500
1)
#1875000
0)
#1937500
1)
#2000000
0)
#2062500
1)
#2125000
0)
#2187500
1)
#2250000
0)
#2312500
1)
#2375000
0)
#2437500
1+
1)
#2500000
0)
#2562500
1"
1)
#2625000
0)
#2687500
1)
#2750000
0)
#2812500
1)
#2875000
0)
#2937500
1)
#3000000
0)
#3062500
1)
#3125000
0)
#3187500
1)
#3250000
0)
#3312500
1)
#3375000
0)
#3437500
1)
#3500000
0)
#3562500
1)
#3625000
0)
#3687500
b11000001 B
1)
#3750000
0)
#3812500
11
1-
1*
b11001010110010101011111010111110 (
b11001010110010101011111010111110 /
b11000001 ,
b11000001 0
b11000001 4
1)
#3875000
0)
#3937500
01
0-
0*
b0 (
b0 /
b0 ,
b0 0
b0 4
1!
1#
b11000001 ?
1@
b10000 =
0"
1)
#4000000
0)
#4062500
b1 <
0@
b110 >
1%
0!
0#
1)
#4125000
0)
#4187500
b10 <
1)
#4250000
0)
#4312500
b11 <
1)
#4375000
0)
#4437500
b100 <
1)
#4500000
0)
#4562500
1;
b101 <
19
b1111 =
1)
#4625000
0)
#4687500
1&
b110 :
b10000000 $
b10000000 2
b10000000 7
b110 <
09
1)
#4750000
0)
#4812500
b111 <
1)
#4875000
0)
#4937500
b1000 <
1)
#5000000
0)
#5062500
b1001 <
1)
#5125000
0)
#5187500
0;
b0 <
1A
b1110 =
1)
#5250000
0)
#5312500
b1 <
0A
b101 >
0&
1)
#5375000
0)
#5437500
b10 <
1)
#5500000
0)
#5562500
b11 <
1)
#5625000
0)
#5687500
b100 <
1)
#5750000
0)
#5812500
1;
b101 <
19
b1101 =
1)
#5875000
0)
#5937500
1&
b101 :
b11000000 $
b11000000 2
b11000000 7
b110 <
09
1)
#6000000
0)
#6062500
b111 <
1)
#6125000
0)
#6187500
b1000 <
1)
#6250000
0)
#6312500
b1001 <
1)
#6375000
0)
#6437500
0;
b0 <
1A
b1100 =
1)
#6500000
0)
#6562500
b1 <
0A
0%
b100 >
0&
1)
#6625000
0)
#6687500
b10 <
1)
#6750000
0)
#6812500
b11 <
1)
#6875000
0)
#6937500
b100 <
1)
#7000000
0)
#7062500
1;
b101 <
19
b1011 =
1)
#7125000
0)
#7187500
1&
b100 :
b110 <
09
1)
#7250000
0)
#7312500
b111 <
1)
#7375000
0)
#7437500
b1000 <
1)
#7500000
0)
#7562500
b1001 <
1)
#7625000
0)
#7687500
0;
b0 <
1A
b1010 =
1)
#7750000
0)
#7812500
b1 <
0A
b11 >
0&
1)
#7875000
0)
#7937500
b10 <
1)
#8000000
0)
#8062500
b11 <
1)
#8125000
0)
#8187500
b100 <
1)
#8250000
0)
#8312500
1;
b101 <
19
b1001 =
1)
#8375000
0)
#8437500
1&
b11 :
b110 <
09
1)
#8500000
0)
#8562500
b111 <
1)
#8625000
0)
#8687500
b1000 <
1)
#8750000
0)
#8812500
b1001 <
1)
#8875000
0)
#8937500
0;
b0 <
1A
b1000 =
1)
#9000000
0)
#9062500
b1 <
0A
b10 >
0&
1)
#9125000
0)
#9187500
b10 <
1)
#9250000
0)
#9312500
b11 <
1)
#9375000
0)
#9437500
b100 <
1)
#9500000
0)
#9562500
1;
b101 <
19
b111 =
1)
#9625000
0)
#9687500
1&
b10 :
b110 <
09
1)
#9750000
0)
#9812500
b111 <
1)
#9875000
0)
#9937500
b1000 <
1)
#10000000
0)
#10062500
b1001 <
1)
#10125000
0)
#10187500
0;
b0 <
1A
b110 =
1)
#10250000
0)
#10312500
b1 <
0A
b1 >
0&
1)
#10375000
0)
#10437500
b10 <
1)
#10500000
0)
#10562500
b11 <
1)
#10625000
0)
#10687500
b100 <
1)
#10750000
0)
#10812500
1;
b101 <
19
b101 =
1)
#10875000
0)
#10937500
1&
b1 :
b110 <
09
1)
#11000000
0)
#11062500
b111 <
1)
#11125000
0)
#11187500
b1000 <
1)
#11250000
0)
#11312500
b1001 <
1)
#11375000
0)
#11437500
0;
b0 <
1A
b100 =
1)
#11500000
0)
#11562500
b1 <
0A
b0 >
0&
1)
#11625000
0)
#11687500
b10 <
1)
#11750000
0)
#11812500
b11 <
1)
#11875000
0)
#11937500
b100 <
1)
#12000000
0)
#12062500
1;
b101 <
19
b11 =
1)
#12125000
0)
#12187500
1&
b0 :
b110 <
09
1)
#12250000
0)
#12312500
b111 <
1)
#12375000
0)
#12437500
b1000 <
1)
#12500000
0)
#12562500
b1001 <
1)
#12625000
0)
#12687500
0;
b0 <
1A
b10 =
1)
#12750000
0)
#12812500
b1 <
0A
1%
b111 >
0&
1)
#12875000
0)
#12937500
b10 <
1)
#13000000
0)
#13062500
b11 <
1)
#13125000
0)
#13187500
b100 <
1)
#13250000
0)
#13312500
1;
b101 <
19
b1 =
1)
#13375000
0)
#13437500
1&
18
b111 :
b11000001 $
b11000001 2
b11000001 7
b110 <
09
1)
#13500000
0)
#13562500
b111 <
08
1)
#13625000
0)
#13687500
b1000 <
1)
#13750000
0)
#13812500
b1001 <
1)
#13875000
0)
#13937500
0;
b0 <
1A
b0 =
1)
#14000000
0)
#14062500
b10111110 B
1"
0A
b110 >
0&
1)
#14125000
0)
#14187500
11
b111 >
1-
1*
b11001010110010101011111010111110 (
b11001010110010101011111010111110 /
b10111110 ,
b10111110 0
b10111110 4
1)
#14250000
0)
#14312500
01
0-
0*
b0 (
b0 /
b0 ,
b0 0
b0 4
b10000 =
0"
b10111110 ?
1@
1!
1#
1)
#14375000
0)
#14437500
0!
0#
b110 >
0@
b1 <
1)
#14500000
0)
#14562500
b10 <
1)
#14625000
0)
#14687500
b11 <
1)
#14750000
0)
#14812500
b100 <
1)
#14875000
0)
#14937500
1;
b101 <
19
b1111 =
1)
#15000000
0)
#15062500
b110 <
09
b110 :
1&
1)
#15125000
0)
#15187500
b111 <
1)
#15250000
0)
#15312500
b1000 <
1)
#15375000
0)
#15437500
b1001 <
1)
#15500000
0)
#15562500
0;
b0 <
1A
b1110 =
1)
#15625000
0)
#15687500
0&
0%
b101 >
b1 <
0A
1)
#15750000
0)
#15812500
b10 <
1)
#15875000
0)
#15937500
b11 <
1)
#16000000
0)
#16062500
b100 <
1)
#16125000
0)
#16187500
1;
b101 <
19
b1101 =
1)
#16250000
0)
#16312500
b110 <
09
b101 :
b10000001 $
b10000001 2
b10000001 7
1&
1)
#16375000
0)
#16437500
b111 <
1)
#16500000
0)
#16562500
b1000 <
1)
#16625000
0)
#16687500
b1001 <
1)
#16750000
0)
#16812500
0;
b0 <
1A
b1100 =
1)
#16875000
0)
#16937500
0&
1%
b100 >
b1 <
0A
1)
#17000000
0)
#17062500
b10 <
1)
#17125000
0)
#17187500
b11 <
1)
#17250000
0)
#17312500
b100 <
1)
#17375000
0)
#17437500
1;
b101 <
19
b1011 =
1)
#17500000
0)
#17562500
b110 <
09
b100 :
b10100001 $
b10100001 2
b10100001 7
1&
1)
#17625000
0)
#17687500
b111 <
1)
#17750000
0)
#17812500
b1000 <
1)
#17875000
0)
#17937500
b1001 <
1)
#18000000
0)
#18062500
0;
b0 <
1A
b1010 =
1)
#18125000
0)
#18187500
0&
b11 >
b1 <
0A
1)
#18250000
0)
#18312500
b10 <
1)
#18375000
0)
#18437500
b11 <
1)
#18500000
0)
#18562500
b100 <
1)
#18625000
0)
#18687500
1;
b101 <
19
b1001 =
1)
#18750000
0)
#18812500
b110 <
09
b11 :
b10110001 $
b10110001 2
b10110001 7
1&
1)
#18875000
0)
#18937500
b111 <
1)
#19000000
0)
#19062500
b1000 <
1)
#19125000
0)
#19187500
b1001 <
1)
#19250000
0)
#19312500
0;
b0 <
1A
b1000 =
1)
#19375000
0)
#19437500
0&
b10 >
b1 <
0A
1)
#19500000
0)
#19562500
b10 <
1)
#19625000
0)
#19687500
b11 <
1)
#19750000
0)
#19812500
b100 <
1)
#19875000
0)
#19937500
1;
b101 <
19
b111 =
1)
#20000000
0)
#20062500
b110 <
09
b10 :
b10111001 $
b10111001 2
b10111001 7
1&
1)
#20125000
0)
#20187500
b111 <
1)
#20250000
0)
#20312500
b1000 <
1)
#20375000
0)
#20437500
b1001 <
1)
#20500000
0)
#20562500
0;
b0 <
1A
b110 =
1)
#20625000
0)
#20687500
0&
b1 >
b1 <
0A
1)
#20750000
0)
#20812500
b10 <
1)
#20875000
0)
#20937500
b11 <
1)
#21000000
0)
#21062500
b100 <
1)
#21125000
0)
#21187500
1;
b101 <
19
b101 =
1)
#21250000
0)
#21312500
b110 <
09
b1 :
b10111101 $
b10111101 2
b10111101 7
1&
1)
#21375000
0)
#21437500
b111 <
1)
#21500000
0)
#21562500
b1000 <
1)
#21625000
0)
#21687500
b1001 <
1)
#21750000
0)
#21812500
0;
b0 <
1A
b100 =
1)
#21875000
0)
#21937500
0&
b0 >
b1 <
0A
1)
#22000000
0)
#22062500
b10 <
1)
#22125000
0)
#22187500
b11 <
1)
#22250000
0)
#22312500
b100 <
1)
#22375000
0)
#22437500
1;
b101 <
19
b11 =
1)
#22500000
0)
#22562500
b110 <
09
b0 :
b10111111 $
b10111111 2
b10111111 7
1&
1)
#22625000
0)
#22687500
b111 <
1)
#22750000
0)
#22812500
b1000 <
1)
#22875000
0)
#22937500
b1001 <
1)
#23000000
0)
#23062500
0;
b0 <
1A
b10 =
1)
#23125000
0)
#23187500
0&
0%
b111 >
b1 <
0A
1)
#23250000
0)
#23312500
b10 <
1)
#23375000
0)
#23437500
b11 <
1)
#23500000
0)
#23562500
b100 <
1)
#23625000
0)
#23687500
1;
b101 <
19
b1 =
1)
#23750000
0)
#23812500
b110 <
09
18
b111 :
b10111110 $
b10111110 2
b10111110 7
1&
1)
#23875000
0)
#23937500
08
b111 <
1)
#24000000
0)
#24062500
b1000 <
1)
#24125000
0)
#24187500
b1001 <
1)
#24250000
0)
#24312500
0;
b0 <
1A
b0 =
1)
#24375000
0)
#24437500
b11101111 B
0&
1%
b110 >
1"
0A
1)
#24500000
0)
#24562500
11
b111 >
1-
1*
b11001010110010101011111010111110 (
b11001010110010101011111010111110 /
b11101111 ,
b11101111 0
b11101111 4
1)
#24625000
0)
#24687500
01
0-
0*
b0 (
b0 /
b0 ,
b0 0
b0 4
1!
1#
b11101111 ?
1@
b10000 =
0"
1)
#24750000
0)
#24812500
b1 <
0@
b110 >
0!
0#
1)
#24875000
0)
#24937500
b10 <
1)
#25000000
0)
#25062500
b11 <
1)
#25125000
0)
#25187500
b100 <
1)
#25250000
0)
#25312500
1;
b101 <
19
b1111 =
1)
#25375000
0)
#25437500
1&
b110 :
b110 <
09
1)
#25500000
0)
#25562500
b111 <
1)
#25625000
0)
#25687500
b1000 <
1)
#25750000
0)
#25812500
b1001 <
1)
#25875000
0)
#25937500
0;
b0 <
1A
b1110 =
1)
#26000000
0)
#26062500
b1 <
0A
b101 >
0&
1)
#26125000
0)
#26187500
b10 <
1)
#26250000
0)
#26312500
b11 <
1)
#26375000
0)
#26437500
b100 <
1)
#26500000
0)
#26562500
1;
b101 <
19
b1101 =
1)
#26625000
0)
#26687500
1&
b101 :
b11111110 $
b11111110 2
b11111110 7
b110 <
09
1)
#26750000
0)
#26812500
b111 <
1)
#26875000
0)
#26937500
b1000 <
1)
#27000000
0)
#27062500
b1001 <
1)
#27125000
0)
#27187500
0;
b0 <
1A
b1100 =
1)
#27250000
0)
#27312500
b1 <
0A
b100 >
0&
1)
#27375000
0)
#27437500
b10 <
1)
#27500000
0)
#27562500
b11 <
1)
#27625000
0)
#27687500
b100 <
1)
#27750000
0)
#27812500
1;
b101 <
19
b1011 =
1)
#27875000
0)
#27937500
1&
b100 :
b110 <
09
1)
#28000000
0)
#28062500
b111 <
1)
#28125000
0)
#28187500
b1000 <
1)
#28250000
0)
#28312500
b1001 <
1)
#28375000
0)
#28437500
0;
b0 <
1A
b1010 =
1)
#28500000
0)
#28562500
b1 <
0A
0%
b11 >
0&
1)
#28625000
0)
#28687500
b10 <
1)
#28750000
0)
#28812500
b11 <
1)
#28875000
0)
#28937500
b100 <
1)
#29000000
0)
#29062500
1;
b101 <
19
b1001 =
1)
#29125000
0)
#29187500
1&
b11 :
b11101110 $
b11101110 2
b11101110 7
b110 <
09
1)
#29250000
0)
#29312500
b111 <
1)
#29375000
0)
#29437500
b1000 <
1)
#29500000
0)
#29562500
b1001 <
1)
#29625000
0)
#29687500
0;
b0 <
1A
b1000 =
1)
#29750000
0)
#29812500
b1 <
0A
1%
b10 >
0&
1)
#29875000
0)
#29937500
b10 <
1)
#30000000
0)
#30062500
b11 <
1)
#30125000
0)
#30187500
b100 <
1)
#30250000
0)
#30312500
1;
b101 <
19
b111 =
1)
#30375000
0)
#30437500
1&
b10 :
b110 <
09
1)
#30500000
0)
#30562500
b111 <
1)
#30625000
0)
#30687500
b1000 <
1)
#30750000
0)
#30812500
b1001 <
1)
#30875000
0)
#30937500
0;
b0 <
1A
b110 =
1)
#31000000
0)
#31062500
b1 <
0A
b1 >
0&
1)
#31125000
0)
#31187500
b10 <
1)
#31250000
0)
#31312500
b11 <
1)
#31375000
0)
#31437500
b100 <
1)
#31500000
0)
#31562500
1;
b101 <
19
b101 =
1)
#31625000
0)
#31687500
1&
b1 :
b110 <
09
1)
#31750000
0)
#31812500
b111 <
1)
#31875000
0)
#31937500
b1000 <
1)
#32000000
0)
#32062500
b1001 <
1)
#32125000
0)
#32187500
0;
b0 <
1A
b100 =
1)
#32250000
0)
#32312500
b1 <
0A
b0 >
0&
1)
#32375000
0)
#32437500
b10 <
1)
#32500000
0)
#32562500
b11 <
1)
#32625000
0)
#32687500
b100 <
1)
#32750000
0)
#32812500
1;
b101 <
19
b11 =
1)
#32875000
0)
#32937500
1&
b0 :
b110 <
09
1)
#33000000
0)
#33062500
b111 <
1)
#33125000
0)
#33187500
b1000 <
1)
#33250000
0)
#33312500
b1001 <
1)
#33375000
0)
#33437500
0;
b0 <
1A
b10 =
1)
#33500000
0)
#33562500
b1 <
0A
b111 >
0&
1)
#33625000
0)
#33687500
b10 <
1)
#33750000
0)
#33812500
b11 <
1)
#33875000
0)
#33937500
b100 <
1)
#34000000
0)
#34062500
1;
b101 <
19
b1 =
1)
#34125000
0)
#34187500
1&
18
b111 :
b11101111 $
b11101111 2
b11101111 7
b110 <
09
1)
#34250000
0)
#34312500
b111 <
08
1)
#34375000
0)
#34437500
b1000 <
1)
#34500000
0)
#34562500
b1001 <
1)
#34625000
0)
#34687500
0;
b0 <
1A
b0 =
1)
#34750000
0)
#34812500
1"
0A
b110 >
0&
1)
#34875000
0)
#34937500
b111 >
1)
