logistart/logistart.v
//Tinyfpga BX - LogicShield

module logistart(
input [7:0] switches,
output [7:0] leds
);

assign leds = switches;

endmodule

test_rom/rom.v
//rom.v

module rom256(input clk,
			input wen,
			input [7:0] addr,
			input [31:0] wdata,
			output reg [31:0] rdata);
			
  reg [31:0] mem [0:255];
  
 // initial mem[0] = 32'haabbccdd;
  
  initial begin
		$readmemh("test.hex4", mem);
  end
  
  always @(posedge clk) begin
        if (wen) mem[addr] <= wdata;
        rdata <= mem[addr];
  end
endmodule

test_rom/top.v
// look in pins.pcf for all the pin names on the TinyFPGA BX board
`include "logistart.v"
`include "rom.v"

module top (
	input PIN_1, 
	input PIN_2,
	input PIN_3,
	input PIN_4,
	input PIN_5,
	input PIN_6,
	input PIN_7,
	input PIN_8,
	output PIN_9,
	output PIN_10,
	output PIN_11,
	output PIN_12,
	output PIN_13,
	output PIN_14,
	output PIN_15,
	output PIN_16,	
	input PIN_17,
	input PIN_18,
	input PIN_19,
	input PIN_20,    
	input CLK,
    output USBPU  // USB pull-up resistor
);
    // drive USB pull-up resistor to '0' to disable USB
	assign USBPU = 0;
	
	wire [7:0] switches;
	assign switches = {PIN_8,PIN_7,PIN_6,PIN_5,PIN_4,PIN_3,PIN_2,PIN_1};
	
	wire [7:0] leds;
	assign {PIN_16,PIN_15,PIN_14,PIN_13,PIN_12,PIN_11,PIN_10,PIN_9} = leds;
	
	wire [3:0] pushbuttons;
	assign pushbuttons = {PIN_17,PIN_18,PIN_19,PIN_20};
	
	//logistart logi1(.switches(switches),	
	//			    .leds(leds));    
	
	wire wen;
	wire clk;
	wire [7:0] addr;
	wire [31:0] rdata;
	wire [31:0] wdata;
		
	assign wen = 0; //Only used as ROM 
	assign clk = CLK;
	assign wdata = 32'h0000_0000;
	
	rom256 mymem(.clk(clk),
			   .wen(wen),
			   .addr(addr),
			   .wdata(wdata),
			   .rdata(rdata));
	
	reg [7:0] leds_reg;

	always @(*) begin
		case(pushbuttons)
			4'b0001: leds_reg = rdata[7:0]; 
			4'b0010: leds_reg = rdata[15:8];
			4'b0100: leds_reg = rdata[23:16];
			4'b1000: leds_reg = rdata[31:24];
			default: leds_reg = 32'h0000_0000;
		endcase
	end

	assign addr = switches;	
	assign leds = leds_reg;				    
    
endmodule

test_rom/top_tb.v
//top_tb.v

`timescale 1ns/10ps

`include "top.v"

module top_tb;

/*
reg PIN_1; 
reg PIN_2;
reg PIN_3;
reg PIN_4;
reg PIN_5;
reg PIN_6;
reg PIN_7;
reg PIN_8;

wire PIN_9,
wire PIN_10,
wire PIN_11,
wire PIN_12,
wire PIN_13,
wire PIN_14,
	output PIN_15,
	output PIN_16,	
	input PIN_17,
	input PIN_18,
	input PIN_19,
	input PIN_20,    
	*/
reg [7:0] switches;
wire [7:0] leds;
reg [3:0] pushbuttons;

reg CLK;
wire USBPU;  // USB pull-up resistor

top mytop(.PIN_1(switches[0]),
		  .PIN_2(switches[1]),
		  .PIN_3(switches[2]),
		  .PIN_4(switches[3]),
		  .PIN_5(switches[4]),
		  .PIN_6(switches[5]),
		  .PIN_7(switches[6]),
		  .PIN_8(switches[7]),
		  .PIN_9(leds[0]),
		  .PIN_10(leds[1]),
		  .PIN_11(leds[2]),
		  .PIN_12(leds[3]),
		  .PIN_13(leds[4]),
		  .PIN_14(leds[5]),
		  .PIN_15(leds[6]),
		  .PIN_16(leds[7]),
		  .PIN_17(pushbuttons[0]),
		  .PIN_18(pushbuttons[1]),
		  .PIN_19(pushbuttons[2]),
		  .PIN_20(pushbuttons[3]),
		  .CLK(CLK),
		  .USBPU(USBPU));
		
initial begin
		$monitor("%d\t%H\t%h\n",$time,pushbuttons,leds);
end  

initial begin

	
	$dumpfile("dump.vcd");
	$dumpvars(0,mytop);
	CLK = 0;
	switches = 8'h00;
	pushbuttons = 4'b0000;
	
	
	#20 pushbuttons = 4'b0001; 
	#20 pushbuttons = 4'b0010;
	#20 pushbuttons = 4'b0100;
	#20 pushbuttons = 4'b1000;	
	#20 pushbuttons = 4'b0000;	
		switches = 8'h01;
	#20 pushbuttons = 4'b0001;
	#20 pushbuttons = 4'b0010;
	#20 pushbuttons = 4'b0100;
	#20 pushbuttons = 4'b1000;	
	#20 pushbuttons = 4'b0000;	
		
	
	#1000 $finish;
end

always begin
	#5 CLK = ~CLK;
end

endmodule

test_rom/dump.vcd
$date
	Tue Jun  9 11:02:53 2020
$end
$version
	Icarus Verilog
$end
$timescale
	10ps
$end
$scope module top_tb $end
$scope module mytop $end
$var wire 1 ! CLK $end
$var wire 1 " PIN_1 $end
$var wire 1 # PIN_17 $end
$var wire 1 $ PIN_18 $end
$var wire 1 % PIN_19 $end
$var wire 1 & PIN_2 $end
$var wire 1 ' PIN_20 $end
$var wire 1 ( PIN_3 $end
$var wire 1 ) PIN_4 $end
$var wire 1 * PIN_5 $end
$var wire 1 + PIN_6 $end
$var wire 1 , PIN_7 $end
$var wire 1 - PIN_8 $end
$var wire 1 . USBPU $end
$var wire 8 / addr [7:0] $end
$var wire 1 0 clk $end
$var wire 32 1 wdata [31:0] $end
$var wire 1 2 wen $end
$var wire 8 3 switches [7:0] $end
$var wire 32 4 rdata [31:0] $end
$var wire 4 5 pushbuttons [3:0] $end
$var wire 8 6 leds [7:0] $end
$var wire 1 7 PIN_9 $end
$var wire 1 8 PIN_16 $end
$var wire 1 9 PIN_15 $end
$var wire 1 : PIN_14 $end
$var wire 1 ; PIN_13 $end
$var wire 1 < PIN_12 $end
$var wire 1 = PIN_11 $end
$var wire 1 > PIN_10 $end
$var reg 8 ? leds_reg [7:0] $end
$scope module mymem $end
$var wire 8 @ addr [7:0] $end
$var wire 1 0 clk $end
$var wire 32 A wdata [31:0] $end
$var wire 1 2 wen $end
$var reg 32 B rdata [31:0] $end
$upscope $end
$upscope $end
$upscope $end
$enddefinitions $end
#0
$dumpvars
bx B
b0 A
b0 @
b0 ?
0>
0=
0<
0;
0:
09
08
07
b0 6
b0 5
bx 4
b0 3
02
b0 1
00
b0 /
0.
0-
0,
0+
0*
0)
0(
0'
0&
0%
0$
0#
0"
0!
$end
#500
b10110000010111001011111101 4
b10110000010111001011111101 B
10
1!
#1000
00
0!
#1500
10
1!
#2000
1>
b10 6
b10 ?
b1000 5
1#
00
0!
#2500
10
1!
#3000
00
0!
#3500
10
1!
#4000
18
19
0>
17
b11000001 6
b11000001 ?
0#
b100 5
1$
00
0!
#4500
10
1!
#5000
00
0!
#5500
10
1!
#6000
08
1:
1;
1>
07
b1110010 6
b1110010 ?
0$
b10 5
1%
00
0!
#6500
10
1!
#7000
00
0!
#7500
10
1!
#8000
18
1<
1=
0>
17
b11111101 6
b11111101 ?
0%
b1 5
1'
00
0!
#8500
10
1!
#9000
00
0!
#9500
10
1!
#10000
08
09
0:
0;
0<
0=
07
b0 6
b0 ?
b1 /
b1 @
b1 3
1"
b0 5
0'
00
0!
#10500
b1111111100000000001100010011 4
b1111111100000000001100010011 B
10
1!
#11000
00
0!
#11500
10
1!
#12000
1<
1=
1>
17
b1111 6
b1111 ?
b1000 5
1#
00
0!
#12500
10
1!
#13000
00
0!
#13500
10
1!
#14000
18
19
1:
1;
0<
0=
0>
07
b11110000 6
b11110000 ?
0#
b100 5
1$
00
0!
#14500
10
1!
#15000
00
0!
#15500
10
1!
#16000
08
09
0:
0;
1>
17
b11 6
b11 ?
0$
b10 5
1%
00
0!
#16500
10
1!
#17000
00
0!
#17500
10
1!
#18000
1;
b10011 6
b10011 ?
0%
b1 5
1'
00
0!
#18500
10
1!
#19000
00
0!
#19500
10
1!
#20000
0;
0>
07
b0 6
b0 ?
b0 5
0'
00
0!
