spi_master_saul/SPI_Master.v
`ifndef SPI_MASTER_V
`define SPI_MASTER_V
	
module SPI_master_pico(
		input clk,
		input [31:0] addr, 
		input [WIDTH-1:0] wdata,	
		input wen, 
		input resetn, 	
		input mem_valid,
		input mem_ready,
		output reg mem_port_ready,
		output reg [WIDTH-1:0] rx_data,
		output reg tx_ready 
);

 	parameter ADDR = 32'h0000_0000; //This parameter must be initialized during instantiation!
 	parameter WIDTH = 8;

 	reg [7:0] tx_byte; // New byte to tx
 	 
 	wire tx_start;
 	
 	assign tx_start = ((addr == ADDR) && mem_valid && wen)? 1'b1 : 1'b0;
 	
 	//bus interface
 	always @(posedge clk) begin
 		if (resetn == 1'b0) begin
 			rx_data <= 0;
 			mem_port_ready <= 0; 			
 			tx_byte <= 0;
 		end else if (mem_valid && (addr == ADDR)) begin
 			mem_port_ready <= (!mem_ready)? 1'b1 : 1'b0; //activates only 1 cycle and only if another device has not already activated mem_ready!
 			
 			if (wen) begin //Copy the data and start the tx 
 				tx_byte <= wdata;
 			end
 		end else begin
 			mem_port_ready <= 1'b0;
 		end				
 	end    
 	
 	//Transmitter 
 	localparam IDLE 	= 2'b00;
 	localparam TX 		= 2'b01;
 	localparam CLEAN_UP	= 2'b11;
 	
 	reg [1:0] SPI_state;
 	
 	always @(posedge clk) begin
 		if (resetn == 1'b0) begin
 			tx_ready <= 1;
 			SPI_state = IDLE;
 		end else begin
 			
 			case (SPI_state)
 				IDLE:
 					begin
 						if (tx_start == 1'b1) begin
 							tx_ready <= 0;
 							SPI_state <= TX; 						
 						end else begin
 							SPI_state <= IDLE;
 							tx_ready <= 1;
 						end
 					end
 				TX:
 					begin
 						rx_data <= tx_byte;
 						SPI_state <= CLEAN_UP;
 					end
 				CLEAN_UP:
 					begin
 						tx_ready <= 1;
 						SPI_state <= IDLE;
 					end
 				default:
 					SPI_state <= IDLE;
 			endcase 			
 		end
 	end
 	
endmodule
	
	
`endif

spi_master_saul/SPI_Master_Pico_TB.sv
///////////////////////////////////////////////////////////////////////////////
// Description:       Simple test bench for SPI Master module
///////////////////////////////////////////////////////////////////////////////
`timescale 1ns/1ps

`include "SPI_Master.v"

`define CLK_FREQ 16000000
`define SPI_FREQ 1600000
`define SPI_MASTER 32'hcaca_bebe

module SPI_Master_Pico_TB ();
  
  //parameter SPI_MODE = 0; // CPOL = 0, CPHA = 0
    
  parameter CLKS_PER_HALF_BIT = (`CLK_FREQ/`SPI_FREQ)/2;
  parameter CLK_PERIOD = 62.5;  // Period Clock TinyFpga 1/16 MHz

  logic resetn = 1'b0;
  logic clk = 1'b0;
  logic [11:0] Clks_per_half_bit = CLKS_PER_HALF_BIT;
  logic [31:0] addr = 0;
  logic wstrobe = 0;
  logic [7:0] wdata = 0; //data to be transmited	
  logic mem_valid = 0;
  logic mem_ready;
  logic spi_master_ready; //Aknowledge that address has been read
  logic spi_master_tx_int_flag;	
  logic [7:0] rx_data;
  //logic SPI_Clk;
  //logic SPI_MISO;
  //logic SPI_MOSI;

  assign mem_ready = spi_master_ready; 
  
  /*
  SPI_Master_Pico #(.ADDR(`SPI_MASTER)) spi(
  	.rstn(rstn),
  	.clk(clk),
  	.Clks_per_half_bit(Clks_per_half_bit),
  	.addr(addr),
  	.wen(wstrobe),
  	.wdata(wdata), //data to be transmited	
  	.mem_valid(mem_valid),
  	.mem_ready(mem_ready),
  	.spi_master_ready(spi_master_ready), //Aknowledge that address has been read
  	.spi_master_tx_int_flag(spi_master_tx_int_flag),	
  	.rx_data(rx_data),	
  	.SPI_Clk(SPI_Clk),
  	.SPI_MISO(SPI_MOSI),
  	.SPI_MOSI(SPI_MOSI) //Back to back test
  );
  */
  SPI_master_pico #(.ADDR(`SPI_MASTER)) spi(
  		.clk(clk),
  		.addr(addr), 
  		.wdata(wdata),	
  		.wen(wstrobe), 
  		.resetn(resetn), 	
  		.mem_valid(mem_valid),
  		.mem_ready(mem_ready),
  		.mem_port_ready(spi_master_ready),
  		.rx_data(rx_data),
  		.tx_ready(spi_master_tx_int_flag) //High when idle, Low when busy
  		);
  
  // Clock Generator:
  always #(CLK_PERIOD) clk = ~clk;

  // Sends a single byte from master.
  task SendSingleByte(input [7:0] data);
    @(posedge clk);
     wdata <= data;
   	 addr <= `SPI_MASTER;
   	 mem_valid <= 1;
   	 wstrobe <= 1;
    
    @(posedge clk);
     wdata <= 0;
     addr <= 0;
     mem_valid <= 0;
     wstrobe <= 1'b0;
    @(posedge spi_master_tx_int_flag);
     //repeat(100) @(posedge clk);
  endtask // SendSingleByte

  
  initial
    begin
      // Required for EDA Playground
      $dumpfile("dump.vcd"); 
      $dumpvars;
      
      repeat(10) @(posedge clk);
      resetn = 1'b0;
      repeat(10) @(posedge clk);
      resetn = 1'b1;
      repeat(10) @(posedge clk);
      
      // Test single byte
      SendSingleByte(8'hC1);
      $display("Sent out 0xC1, Received 0x%X", rx_data); 
      
      // Test double byte
      SendSingleByte(8'hBE);
      $display("Sent out 0xBE, Received 0x%X", rx_data); 
      SendSingleByte(8'hEF);
      $display("Sent out 0xEF, Received 0x%X", rx_data); 
      repeat(100) @(posedge clk);
      $finish();      
    end // initial begin

endmodule // SPI_Slave

spi_master_saul/dump.vcd
$date
	Thu Nov 12 23:53:45 2020
$end
$version
	Icarus Verilog
$end
$timescale
	1ps
$end
$scope module SPI_Master_Pico_TB $end
$var wire 1 ! mem_ready $end
$var wire 1 " spi_master_tx_int_flag $end
$var wire 1 # spi_master_ready $end
$var wire 8 $ rx_data [7:0] $end
$var reg 12 % Clks_per_half_bit [11:0] $end
$var reg 32 & addr [31:0] $end
$var reg 1 ' clk $end
$var reg 1 ( mem_valid $end
$var reg 1 ) resetn $end
$var reg 8 * wdata [7:0] $end
$var reg 1 + wstrobe $end
$scope module spi $end
$var wire 32 , addr [31:0] $end
$var wire 1 ' clk $end
$var wire 1 ! mem_ready $end
$var wire 1 ( mem_valid $end
$var wire 1 ) resetn $end
$var wire 8 - wdata [7:0] $end
$var wire 1 + wen $end
$var reg 2 . SPI_state [1:0] $end
$var reg 1 # mem_port_ready $end
$var reg 8 / rx_data [7:0] $end
$var reg 8 0 tx_byte [7:0] $end
$var reg 1 " tx_ready $end
$var reg 1 1 tx_start $end
$upscope $end
$scope task SendSingleByte $end
$var reg 8 2 data [7:0] $end
$upscope $end
$upscope $end
$enddefinitions $end
#0
$dumpvars
bx 2
x1
bx 0
bx /
bx .
b0 -
b0 ,
0+
b0 *
0)
0(
0'
b0 &
b101 %
bx $
x#
x"
x!
$end
#62500
01
b0 0
1"
0!
0#
b0 $
b0 /
b0 .
1'
#125000
0'
#187500
1'
#250000
0'
#312500
1'
#375000
0'
#437500
1'
#500000
0'
#562500
1'
#625000
0'
#687500
1'
#750000
0'
#812500
1'
#875000
0'
#937500
1'
#1000000
0'
#1062500
1'
#1125000
0'
#1187500
1'
#1250000
0'
#1312500
1'
#1375000
0'
#1437500
1'
#1500000
0'
#1562500
1'
#1625000
0'
#1687500
1'
#1750000
0'
#1812500
1'
#1875000
0'
#1937500
1'
#2000000
0'
#2062500
1'
#2125000
0'
#2187500
1'
#2250000
0'
#2312500
1'
#2375000
0'
#2437500
1)
1'
#2500000
0'
#2562500
1'
#2625000
0'
#2687500
1'
#2750000
0'
#2812500
1'
#2875000
0'
#2937500
1'
#3000000
0'
#3062500
1'
#3125000
0'
#3187500
1'
#3250000
0'
#3312500
1'
#3375000
0'
#3437500
1'
#3500000
0'
#3562500
1'
#3625000
0'
#3687500
b11000001 2
1'
#3750000
0'
#3812500
1+
1(
b11001010110010101011111010111110 &
b11001010110010101011111010111110 ,
b11000001 *
b11000001 -
1'
#3875000
0'
#3937500
0+
0(
b0 &
b0 ,
b0 *
b0 -
11
0"
b11000001 0
1!
1#
1'
#4000000
0'
#4062500
0!
0#
01
b1 .
1'
#4125000
0'
#4187500
b11 .
b11000001 $
b11000001 /
1'
#4250000
0'
#4312500
b10111110 2
b0 .
1"
1'
#4375000
0'
#4437500
1+
1(
b11001010110010101011111010111110 &
b11001010110010101011111010111110 ,
b10111110 *
b10111110 -
1'
#4500000
0'
#4562500
0+
0(
b0 &
b0 ,
b0 *
b0 -
11
0"
b10111110 0
1!
1#
1'
#4625000
0'
#4687500
01
b1 .
0!
0#
1'
#4750000
0'
#4812500
b11 .
b10111110 $
b10111110 /
1'
#4875000
0'
#4937500
b11101111 2
b0 .
1"
1'
#5000000
0'
#5062500
1+
1(
b11001010110010101011111010111110 &
b11001010110010101011111010111110 ,
b11101111 *
b11101111 -
1'
#5125000
0'
#5187500
0+
0(
b0 &
b0 ,
b0 *
b0 -
11
0"
b11101111 0
1!
1#
1'
#5250000
0'
#5312500
0!
0#
01
b1 .
1'
#5375000
0'
#5437500
b11 .
b11101111 $
b11101111 /
1'
#5500000
0'
#5562500
b0 .
1"
1'
